CvaReader/CvaReader.py
CvaReader/__init__.py
cvareader_veejey6-0.0.1.dist-info/LICENSE
cvareader_veejey6-0.0.1.dist-info/METADATA
cvareader_veejey6-0.0.1.dist-info/WHEEL
cvareader_veejey6-0.0.1.dist-info/top_level.txt
cvareader_veejey6-0.0.1.dist-info/RECORD
